cnvrg_experiment_chart/__init__.py
cnvrg_experiment_chart/chart.py
cnvrg_experiment_chart-0.1.11.dist-info/LICENSE.txt
cnvrg_experiment_chart-0.1.11.dist-info/METADATA
cnvrg_experiment_chart-0.1.11.dist-info/WHEEL
cnvrg_experiment_chart-0.1.11.dist-info/top_level.txt
cnvrg_experiment_chart-0.1.11.dist-info/RECORD
