Metadata-Version: 2.1
Name: cnvrg-experiment-chart
Version: 0.1.11
Summary: Module to supliment the handling of charts in the cnvrgv2 sdk
Home-page: https://github.com/nctiggy/cnvrg_experiment_chart
Author: Craig Smith
Author-email: nctiggy@gmail.com
License: MIT
Project-URL: Documentation, https://cnvrg-experiment-chart.readthedocs.io
Project-URL: Source, https://github.com/nctiggy/cnvrg_experiment_chart
Project-URL: Download, https://pypi.org/project/cnvrg-experiment-chart/
Platform: any
Classifier: Development Status :: 4 - Beta
Classifier: Programming Language :: Python
License-File: LICENSE.txt
Requires-Dist: cnvrgv2
Requires-Dist: importlib-metadata ; python_version < "3.8"
Provides-Extra: testing
Requires-Dist: setuptools ; extra == 'testing'
Requires-Dist: pytest ; extra == 'testing'
Requires-Dist: pytest-cov ; extra == 'testing'
